c2s2/base/__init__.py
c2s2/base/cluster.py
c2s2/base/explain.py
c2s2/base/perturb.py
c2s2/base/test_explain.py
c2s2/base/test_kernel_k_means.py
c2s2/base/test_perturb.py
c2s2/base/consensus/__init__.py
c2s2/base/consensus/_base.py
c2s2/base/consensus/simple.py
c2s2/base/data/__init__.py
c2s2/base/data/_simple.py
c2s2/base/data/simple.py
c2s2/base/model/__init__.py
c2s2/base/model/_base.py
c2s2/base/model/simple.py
c2s2/base/model/test_simple.py
c2s2/base/semsim/__init__.py
c2s2/base/semsim/_base.py
c2s2/base/semsim/_dummy.py
c2s2/base/semsim/_phenomizer.py
c2s2/base/semsim/_phenomizer_io.py
c2s2/base/semsim/test__phenomizer_io.py
c2s2/base/semsim/test_phenomizer.py
c2s2/base/semsim/test_data/tps.csv.gz
c2s2-0.2.0.dist-info/METADATA
c2s2-0.2.0.dist-info/WHEEL
c2s2-0.2.0.dist-info/top_level.txt
c2s2-0.2.0.dist-info/RECORD
