Metadata-Version: 2.1
Name: c2s2
Version: 0.2.0
Summary: Consensus clustering for a number of individuals with HPO terms or phenopackets.
Home-page: https://github.com/monarch-initiative/C2S2
Author: Lex Dingemans, Daniel Danis
Author-email: a.dingemans@radboudumc.nl
License: BSD 3
Keywords: clustering,HPO terms,phenopackets
Requires-Dist: numpy (~=1.19.5)
